MANIFEST.in
setup.py
bin/pilasengine
data/aceituna.png
data/aceituna_burla.png
data/aceituna_grita.png
data/aceituna_risa.png
data/alien.png
data/arboles.png
data/banana.png
data/batalhao.png
data/bomba.png
data/caja.png
data/cielo.png
data/cursordisparo.png
data/disparo.png
data/disparo_laser.png
data/efecto_humo_1.png
data/efecto_humo_2.png
data/ejes.png
data/estrella.png
data/explosion.png
data/explosion.wav
data/fantasma.png
data/fantasma_azul.png
data/flecha.png
data/globo.png
data/humo.png
data/humo2.png
data/icono.ico
data/icono_pausa.png
data/invisible.png
data/manzana.png
data/mapa.png
data/moneda.png
data/monkey_normal.png
data/monkey_shout.png
data/monkey_smile.png
data/mono.png
data/mono_gritar.png
data/mono_reir.png
data/montes.png
data/nave.png
data/ovni.png
data/pacman.png
data/palo.png
data/particula.png
data/pastilla_1.png
data/pasto.png
data/patito.png
data/patito_desde_arriba.png
data/pelota.png
data/piedra_chica.png
data/piedra_grande.png
data/piedra_media.png
data/pilasengine-icono.png
data/pingu.png
data/pixel_player.png
data/planeta_azul.png
data/planeta_marron.png
data/planeta_naranja.png
data/planeta_rojo.png
data/planeta_verde.png
data/plano.png
data/plataformas.png
data/prueba.png
data/punto.png
data/saltar.wav
data/shout.wav
data/sin_imagen.png
data/smile.wav
data/sombra.png
data/sombra_vaca_corriendo.png
data/spacekids.png
data/tick.wav
data/tile_pacman.png
data/tile_pacman.tmx
data/torreta.png
data/tortuga.png
data/vaca_corriendo.png
data/zanahoria_normal.png
data/zanahoria_sonrie.png
data/api/genindex.html
data/api/index.html
data/api/objects.inv
data/api/pilasengine.actores.html
data/api/pilasengine.colisiones.html
data/api/pilasengine.comportamientos.html
data/api/pilasengine.controles.html
data/api/pilasengine.depurador.html
data/api/pilasengine.escenas.html
data/api/pilasengine.eventos.html
data/api/pilasengine.fisica.constantes.html
data/api/pilasengine.fisica.html
data/api/pilasengine.fondos.html
pilas.egg-info/PKG-INFO
pilas.egg-info/SOURCES.txt
pilas.egg-info/dependency_links.txt
pilas.egg-info/not-zip-safe
pilas.egg-info/requires.txt
pilas.egg-info/top_level.txt
