Metadata-Version: 1.0
Name: pilas
Version: 1.4.9
Summary: Pilas Engine - un motor para realizar videojuegos de manera rápida y sencilla.
